hack_anything/__init__.py
hack_anything/hack_tool.py
hack_anything-0.1.5.dist-info/WHEEL
hack_anything-0.1.5.dist-info/METADATA
hack_anything-0.1.5.dist-info/RECORD
