Metadata-Version: 2.1
Name: hack-anything
Version: 0.1.5
Summary: 
Author: Praneeth
Author-email: spraneeth4@gmail.com
Requires-Python: >=3.7,<4.0
Classifier: Programming Language :: Python :: 3
Classifier: Programming Language :: Python :: 3.10
Classifier: Programming Language :: Python :: 3.7
Classifier: Programming Language :: Python :: 3.8
Classifier: Programming Language :: Python :: 3.9
Requires-Dist: tqdm (>=4.62.3,<5.0.0)
